odecloud/__init__.py
odecloud/api/__init__.py
odecloud/api/connection.py
odecloud/api/exceptions.py
odecloud-0.14.2.dist-info/LICENSE
odecloud-0.14.2.dist-info/METADATA
odecloud-0.14.2.dist-info/WHEEL
odecloud-0.14.2.dist-info/RECORD
